Metadata-Version: 2.1
Name: ibrokh
Version: 0.1.0
Summary: SMS
Home-page: https://github.com/Ibrokhim1006/Python-open-sourse.git
Author: Ibrokhim Istamov
Author-email: istamovibrokhim8@gmail.com
License: MIT
License-File: LICENSE
